skim/__init__.py
skim/__main__.py
skim/application/__init__.py
skim/application/config_generator.py
skim/application/image_generator.py
skim/application/keycode_loader.py
skim/application/keycode_transformer.py
skim/application/layer_transformer.py
skim/application/parsers/c2json_parser.py
skim/application/parsers/keybard_parser.py
skim/application/parsers/qmk_color_parser.py
skim/application/parsers/vial_parser.py
skim/application/typst_compiler.py
skim/assets/data/default-config.yaml
skim/assets/data/keycode-mappings.yaml
skim/assets/typst/fonts/Roboto-Black.ttf
skim/assets/typst/fonts/Roboto-Regular.ttf
skim/assets/typst/fonts/Roboto-Thin.ttf
skim/assets/typst/fonts/SymbolsNerdFontMono-Regular.ttf
skim/assets/typst/keymap-layers.typ
skim/assets/typst/keymap-overview.typ
skim/assets/typst/svalboard-keys.typ
skim/assets/typst/svalboard-logo.svg
skim/domain/__init__.py
skim/domain/colors.py
skim/domain/config.py
skim/domain/models.py
skim/ui/cli.py
skim/ui/logging_config.py
qmk_skim-0.4.2.dist-info/WHEEL
qmk_skim-0.4.2.dist-info/entry_points.txt
qmk_skim-0.4.2.dist-info/METADATA
qmk_skim-0.4.2.dist-info/RECORD
