Metadata-Version: 2.3
Name: qmk-skim
Version: 0.4.2
Summary: Svalboard Keymap Image Maker
Keywords: svalboard,keyboard,keymap,layout,image,svg,png,typst
Author: Thiago Alves
Author-email: Thiago Alves <thiago@rapinialves.com>
Classifier: Development Status :: 3 - Alpha
Classifier: Environment :: Console
Classifier: Intended Audience :: End Users/Desktop
Classifier: License :: OSI Approved :: MIT License
Classifier: Operating System :: OS Independent
Classifier: Programming Language :: Python :: 3
Classifier: Programming Language :: Python :: 3.10
Classifier: Programming Language :: Python :: 3.11
Classifier: Programming Language :: Python :: 3.12
Classifier: Topic :: Multimedia :: Graphics
Classifier: Topic :: Utilities
Requires-Dist: click>=8.1.0
Requires-Dist: pyyaml>=6.0
Requires-Dist: typst>=0.12.0
Requires-Python: >=3.10
